lzy_taas/__init__.py
lzy_taas/config.py
lzy_taas/create_project.py
lzy_taas/notebook_generator.py
lzy_taas/upload_to_s3.py
lzy_taas-0.0.2.dist-info/METADATA
lzy_taas-0.0.2.dist-info/WHEEL
lzy_taas-0.0.2.dist-info/top_level.txt
lzy_taas-0.0.2.dist-info/RECORD
