Metadata-Version: 2.1
Name: lzy-taas
Version: 0.0.2
Summary: Python API for TaaS & LZY
Home-page: UNKNOWN
Author: Yandex
License: MIT
Platform: UNKNOWN
Requires-Dist: requests
Requires-Dist: datasphere-python
Requires-Dist: boto3
